mtmscreentocode/.gitignore
mtmscreentocode/.pre-commit-config.yaml
mtmscreentocode/Dockerfile
mtmscreentocode/README.md
mtmscreentocode/build.sh
mtmscreentocode/codegen/__init__.py
mtmscreentocode/codegen/test_utils.py
mtmscreentocode/codegen/utils.py
mtmscreentocode/config.py
mtmscreentocode/custom_types.py
mtmscreentocode/debug/DebugFileWriter.py
mtmscreentocode/debug/__init__.py
mtmscreentocode/evals/__init__.py
mtmscreentocode/evals/config.py
mtmscreentocode/evals/core.py
mtmscreentocode/evals/utils.py
mtmscreentocode/fs_logging/__init__.py
mtmscreentocode/fs_logging/core.py
mtmscreentocode/image_generation/__init__.py
mtmscreentocode/image_generation/core.py
mtmscreentocode/image_generation/replicate.py
mtmscreentocode/image_processing/__init__.py
mtmscreentocode/image_processing/utils.py
mtmscreentocode/llm.py
mtmscreentocode/main.py
mtmscreentocode/mock_llm.py
mtmscreentocode/poetry.lock
mtmscreentocode/prompts/__init__.py
mtmscreentocode/prompts/claude_prompts.py
mtmscreentocode/prompts/imported_code_prompts.py
mtmscreentocode/prompts/screenshot_system_prompts.py
mtmscreentocode/prompts/test_prompts.py
mtmscreentocode/prompts/types.py
mtmscreentocode/routes/evals.py
mtmscreentocode/routes/generate_code.py
mtmscreentocode/routes/home.py
mtmscreentocode/routes/screenshot.py
mtmscreentocode/run_evals.py
mtmscreentocode/run_image_generation_evals.py
mtmscreentocode/start.py
mtmscreentocode/test_llm.py
mtmscreentocode/utils.py
mtmscreentocode/video/utils.py
mtmscreentocode/video_to_app.py
mtmscreentocode/ws/__init__.py
mtmscreentocode/ws/constants.py
mtmscreentocode-0.0.592.dist-info/METADATA
mtmscreentocode-0.0.592.dist-info/WHEEL
mtmscreentocode-0.0.592.dist-info/RECORD
