Metadata-Version: 2.1
Name: mtmscreentocode
Version: 0.0.592
Summary: 
License: MIT
Author: Abi Raja
Author-email: abimanyuraja@gmail.com
Requires-Python: >=3.10,<3.13
Classifier: License :: OSI Approved :: MIT License
Classifier: Programming Language :: Python :: 3
Classifier: Programming Language :: Python :: 3.10
Classifier: Programming Language :: Python :: 3.11
Classifier: Programming Language :: Python :: 3.12
Requires-Dist: aiohttp (>=3.9.5)
Requires-Dist: anthropic (>=0.18.0)
Requires-Dist: beautifulsoup4 (>=4.12.2)
Requires-Dist: fastapi (>=0.104.1)
Requires-Dist: httpx (>=0.27.0)
Requires-Dist: moviepy (>=1.0.3)
Requires-Dist: openai (>=1.2.4)
Requires-Dist: pillow (>=10.3.0)
Requires-Dist: pre-commit (>=3.6.2)
Requires-Dist: pydantic (>=2.5.1)
Requires-Dist: python-dotenv (>=1.0.0)
Requires-Dist: types-pillow (>=10.2.0.20240520)
Requires-Dist: uvicorn (>=0.25.0)
Requires-Dist: websockets (>=12.0)
